capnpy/__init__.pxd
capnpy/__init__.py
capnpy/__main__.py
capnpy/_hash.c
capnpy/_hash.cpython-311-x86_64-linux-musl.so
capnpy/_hash.h
capnpy/_hash.pxd
capnpy/_hash.py
capnpy/_hash.pyx
capnpy/_hash_cpython.c
capnpy/_util.c
capnpy/_util.cpython-311-x86_64-linux-musl.so
capnpy/_util.h
capnpy/_util.pyx
capnpy/annotate.capnp
capnpy/annotate.py
capnpy/annotate_extended.py
capnpy/anypointer.py
capnpy/blob.c
capnpy/blob.cpython-311-x86_64-linux-musl.so
capnpy/blob.pxd
capnpy/blob.py
capnpy/buffered.c
capnpy/buffered.cpython-311-x86_64-linux-musl.so
capnpy/buffered.pxd
capnpy/buffered.py
capnpy/convert_case.py
capnpy/enum.c
capnpy/enum.cpython-311-x86_64-linux-musl.so
capnpy/enum.py
capnpy/filelike.c
capnpy/filelike.cpython-311-x86_64-linux-musl.so
capnpy/filelike.pxd
capnpy/filelike.py
capnpy/list.c
capnpy/list.cpython-311-x86_64-linux-musl.so
capnpy/list.pxd
capnpy/list.py
capnpy/message.c
capnpy/message.cpython-311-x86_64-linux-musl.so
capnpy/message.pxd
capnpy/message.py
capnpy/packing.c
capnpy/packing.cpython-311-x86_64-linux-musl.so
capnpy/packing.pxd
capnpy/packing.py
capnpy/packing.pyx
capnpy/printer.py
capnpy/ptr.c
capnpy/ptr.cpython-311-x86_64-linux-musl.so
capnpy/ptr.h
capnpy/ptr.pxd
capnpy/ptr.py
capnpy/ptr.pyx
capnpy/reflection.py
capnpy/schema.capnp
capnpy/schema.py
capnpy/schema_extended.py
capnpy/struct_.c
capnpy/struct_.cpython-311-x86_64-linux-musl.so
capnpy/struct_.pxd
capnpy/struct_.py
capnpy/type.c
capnpy/type.cpython-311-x86_64-linux-musl.so
capnpy/type.pxd
capnpy/type.py
capnpy/util.py
capnpy/benchmarks/__init__.py
capnpy/benchmarks/benchmarks.capnp
capnpy/benchmarks/benchmarks_base.capnp
capnpy/benchmarks/bigtree.dump
capnpy/benchmarks/support.py
capnpy/benchmarks/test_benchmarks.py
capnpy/benchmarks/test_buffered.py
capnpy/benchmarks/test_ctor.py
capnpy/benchmarks/test_message.py
capnpy/benchmarks/test_unpack.py
capnpy/compiler/__init__.py
capnpy/compiler/compiler.py
capnpy-0.12.0.dist-info/METADATA
capnpy-0.12.0.dist-info/WHEEL
capnpy-0.12.0.dist-info/entry_points.txt
capnpy-0.12.0.dist-info/top_level.txt
capnpy-0.12.0.dist-info/RECORD
capnpy-0.12.0.dist-info/licenses/LICENSE
