Metadata-Version: 2.4
Name: capnpy
Version: 0.12.0
Home-page: https://github.com/antocuni/capnpy
Author: Antonio Cuni
Author-email: anto.cuni@gmail.com
License-File: LICENSE
Requires-Dist: pypytools>=0.3.3
Requires-Dist: docopt
Requires-Dist: packaging
Requires-Dist: six
Requires-Dist: setuptools
Requires-Dist: cython>=0.29.30
Dynamic: author
Dynamic: author-email
Dynamic: description
Dynamic: home-page
Dynamic: license-file
Dynamic: requires-dist
